mdn_sphinx_theme-2016.0.dist-info/DESCRIPTION.rst
mdn_sphinx_theme-2016.0.dist-info/METADATA
mdn_sphinx_theme-2016.0.dist-info/metadata.json
mdn_sphinx_theme-2016.0.dist-info/RECORD
mdn_sphinx_theme-2016.0.dist-info/top_level.txt
mdn_sphinx_theme-2016.0.dist-info/WHEEL
mdn_theme/__init__.py
mdn_theme/mdn/layout.html
mdn_theme/mdn/theme.conf
mdn_theme/mdn/static/mozilla.css_t
mdn_theme/mdn/static/fonts/BebasNeue-webfont.eot
mdn_theme/mdn/static/fonts/BebasNeue-webfont.svg
mdn_theme/mdn/static/fonts/BebasNeue-webfont.ttf
mdn_theme/mdn/static/fonts/BebasNeue-webfont.woff
mdn_theme/mdn/static/fonts/OpenSans-Light-webfont.ttf
mdn_theme/mdn/static/fonts/OpenSans-Light.ttf
mdn_theme/mdn/static/fonts/OpenSans-Regular-webfont.ttf
mdn_theme/mdn/static/fonts/OpenSans-Regular.ttf
mdn_theme/mdn/static/images/bg-gradient-sand.png
mdn_theme/mdn/static/images/bg-sand.png
mdn_theme/mdn/static/images/divider.png
