Metadata-Version: 2.0
Name: mdn-sphinx-theme
Version: 2016.0
Summary: A Sphinx theme for the Mozilla Developer Network
Home-page: https://github.com/mdn/sphinx-theme
Author: Mozilla & Contributors
Author-email: mdn-dev@mozilla.com
License: MPL 2.0
Keywords: sphinx extension theme mdn
Platform: UNKNOWN
Classifier: Development Status :: 5 - Production/Stable
Classifier: Intended Audience :: Developers
Classifier: License :: OSI Approved :: Mozilla Public License 2.0 (MPL 2.0)
Classifier: Operating System :: OS Independent
Classifier: Programming Language :: Python :: 2.7
Classifier: Topic :: Documentation
Classifier: Topic :: Software Development :: Documentation
Requires-Dist: sphinx
